pyneng_quiz/__init__.py
pyneng_quiz/help_table_widget.py
pyneng_quiz/question_table_widget.py
pyneng_quiz/questions.json
pyneng_quiz/questions_en.json
pyneng_quiz/questions_ru.json
pyneng_quiz/questions_uk.json
pyneng_quiz/select_questions_widget.py
pyneng_quiz/termquiz.py
pyneng_quiz-0.7.0.dist-info/LICENSE
pyneng_quiz-0.7.0.dist-info/METADATA
pyneng_quiz-0.7.0.dist-info/WHEEL
pyneng_quiz-0.7.0.dist-info/entry_points.txt
pyneng_quiz-0.7.0.dist-info/top_level.txt
pyneng_quiz-0.7.0.dist-info/RECORD
