Metadata-Version: 2.1
Name: pyneng-quiz
Version: 0.7.0
Summary: CLI tool to run pyneng quiz
Home-page: https://github.com/natenka/pyneng-quiz
Author: Natasha Samoylenko
Author-email: "Natasha Samoylenko" <natasha.samoylenko@gmail.com>
License: MIT
Classifier: License :: OSI Approved :: MIT License
License-File: LICENSE
Requires-Dist: textual (==0.1.18)
Requires-Dist: rich
